pyhunters/__init__.py
pyhunters/core.py
pyhunters/mark.py
pyhunters/settings.py
pyhunters/settings/build_root.py
pyhunters/type_mods/singleton.py
pyhunters-1.0.0.dist-info/METADATA
pyhunters-1.0.0.dist-info/WHEEL
pyhunters-1.0.0.dist-info/RECORD
