Metadata-Version: 2.4
Name: pyhunters
Version: 1.0.0
Summary: a (py)hunter marks its targets
Author-email: Stefan Dalecki <daleckidev@gmail.com>, Dan Kilcullen <devcullen@proton.me>
Classifier: Intended Audience :: Developers
Classifier: Programming Language :: Python :: 3.13
Requires-Python: >=3.11
Requires-Dist: pandas~=2.2
Requires-Dist: pydantic~=2.11
Requires-Dist: varname~=0.13
